vpe_syntax/__init__.py
vpe_syntax/core.py
vpe_syntax/fred.py
vpe_syntax/hl_groups.py
vpe_syntax/language_nesting.py
vpe_syntax/py.typed
vpe_syntax/scheme_tweaker.py
vpe_syntax/web_colours.py
vpe_syntax/resources/c.syn
vpe_syntax/resources/python.syn
vpe_syntax/transformers/__init__.py
vpe_syntax/transformers/rst.py
vpe_syntax-0.2.1.dist-info/METADATA
vpe_syntax-0.2.1.dist-info/WHEEL
vpe_syntax-0.2.1.dist-info/entry_points.txt
vpe_syntax-0.2.1.dist-info/top_level.txt
vpe_syntax-0.2.1.dist-info/RECORD
