Metadata-Version: 2.4
Name: vpe-syntax
Version: 0.2.1
Summary: Tree-sitter based syntax highlighting for Vim
Author-email: Paul Ollis <paul@cleversheep.org>
Project-URL: Homepage, https://github.com/paul-ollis/vpe_syntax
Project-URL: Bug Tracker, https://github.com/paul-ollis/vpe_syntax/issues
Classifier: Development Status :: 3 - Alpha
Classifier: License :: OSI Approved :: MIT License
Classifier: Operating System :: POSIX :: Linux
Classifier: Programming Language :: Python :: 3
Classifier: Programming Language :: Python :: 3.11
Classifier: Environment :: Console
Classifier: Topic :: Education
Requires-Python: <3.13,>=3.11
Requires-Dist: vpe>=0.7.3
Requires-Dist: vpe-sitter>=0.2.1
